Metadata-Version: 1.0
Name: sw-django-rest-auth
Version: 0.0.26
Summary: Soft Way company django restfromework authentication service package.
Home-page: https://github.com/telminov/sw-django-rest-auth
Author: Telminov Sergey
Author-email: UNKNOWN
License: The MIT License
Platform: UNKNOWN
